{
  "type": "Feature",
  "properties": {
    "gn:asciiname":"Kundur marqa",
    "gn:country_code":"PN",
    "gn:dem":54,
    "gn:feature_class":"P",
    "gn:feature_code":"PPL",
    "gn:name":"Kundur marqa",
    "gn:population":0,
    "gn:timezone":"Pacific/Pitcairn",
    "iso:country":"PN",
    "wof:name":"Kundur marqa",
    "wof:placetype":"locality"
},
  "geometry": {"coordinates":[-130.10356999999999,-25.065],"type":"Point"}
}